ccs_data/__init__.py
ccs_data/data/Openstck.PDF
ccs_data/data/Practicals.zip
ccs_data/data/abcd.png
ccs_data/data/manual.zip
ccs_data/data/regisbg.png
ccs_data-0.1.dist-info/METADATA
ccs_data-0.1.dist-info/WHEEL
ccs_data-0.1.dist-info/top_level.txt
ccs_data-0.1.dist-info/RECORD
