Metadata-Version: 2.1
Name: ccs_data
Version: 0.1
Summary: A package with data files for AI practicals
Author: Your Name
